app.py
setup.py
terminal_twitter.egg-info/PKG-INFO
terminal_twitter.egg-info/SOURCES.txt
terminal_twitter.egg-info/dependency_links.txt
terminal_twitter.egg-info/entry_points.txt
terminal_twitter.egg-info/requires.txt
terminal_twitter.egg-info/top_level.txt