Metadata-Version: 1.0
Name: terminal-twitter
Version: 1.0
Summary: A Twitter CLI
Home-page: http://github.com/mavidser/tt
Author: Sid Verma
Author-email: sid@sidverma.net
License: UNKNOWN
Platform: UNKNOWN
